odoo/addons/so_report_hide_price/README.rst
odoo/addons/so_report_hide_price/__init__.py
odoo/addons/so_report_hide_price/__manifest__.py
odoo/addons/so_report_hide_price/models/__init__.py
odoo/addons/so_report_hide_price/models/res_config_settings.py
odoo/addons/so_report_hide_price/models/sale_order.py
odoo/addons/so_report_hide_price/models/sale_order_line.py
odoo/addons/so_report_hide_price/readme/CONFIGURE.rst
odoo/addons/so_report_hide_price/readme/CONTRIBUTORS.rst
odoo/addons/so_report_hide_price/readme/DESCRIPTION.rst
odoo/addons/so_report_hide_price/readme/USAGE.rst
odoo/addons/so_report_hide_price/report/sale_report_templates.xml
odoo/addons/so_report_hide_price/static/description/icon.png
odoo/addons/so_report_hide_price/static/description/index.html
odoo/addons/so_report_hide_price/views/res_config_settings_views.xml
odoo/addons/so_report_hide_price/views/sale_views.xml
odoo_addon_so_report_hide_price-15.0.1.0.0.2.dist-info/METADATA
odoo_addon_so_report_hide_price-15.0.1.0.0.2.dist-info/WHEEL
odoo_addon_so_report_hide_price-15.0.1.0.0.2.dist-info/top_level.txt
odoo_addon_so_report_hide_price-15.0.1.0.0.2.dist-info/RECORD
