Metadata-Version: 2.1
Name: odoo-addon-so_report_hide_price
Version: 15.0.1.0.0.2
Requires-Python: >=3.8
Requires-Dist: odoo>=15.0a,<15.1dev
Summary: Show/Hide price info in sale PDF
Home-page: https://github.com/sygel-technology/sy-sale-reporting
License: AGPL-3
Author: Sygel
Classifier: Programming Language :: Python
Classifier: Framework :: Odoo
Classifier: Framework :: Odoo :: 15.0
Classifier: License :: OSI Approved :: GNU Affero General Public License v3
